{
  "hero": {
    "show": true,
    "title": "Music Program",
    "subtitle": "Cultivating musical excellence, creativity, and lifelong appreciation for the arts",
    "stats": [
      {
        "value": "12+",
        "label": "Music Ensembles",
        "show": true
      },
      {
        "value": "50+",
        "label": "Annual Performances",
        "show": true
      },
      {
        "value": "25+",
        "label": "State Awards",
        "show": true
      }
    ],
    "backgroundImage": "https://images.unsplash.com/photo-1511379938547-c1f69419868d?ixlib=rb-4.0.3&ixid=M3wxMjA3fDB8MHxwaG90by1wYWdlfHx8fGVufDB8fHx8fA%3D%3D&auto=format&fit=crop&w=2070&q=80",
    "backgroundImageShow": true,
    "ctaButton": {
      "label": "View Music Handbook",
      "link": "#",
      "show": true
    }
  },
  "benefits": {
    "show": true,
    "title": "Why Study Music?",
    "description": "Music education provides countless benefits that extend far beyond the rehearsal room",
    "items": [
      {
        "icon": "Brain",
        "title": "Cognitive Development",
        "description": "Enhancing memory, pattern recognition, and mathematical abilities through musical training.",
        "show": true
      },
      {
        "icon": "Heart",
        "title": "Emotional Expression",
        "description": "Providing creative outlets for emotional expression and building confidence.",
        "show": true
      },
      {
        "icon": "Users",
        "title": "Collaborative Skills",
        "description": "Developing teamwork and communication through ensemble performances.",
        "show": true
      },
      {
        "icon": "Trophy",
        "title": "Discipline & Achievement",
        "description": "Cultivating perseverance, goal-setting, and pride in accomplishments.",
        "show": true
      }
    ]
  },
  "categories": {
    "show": true,
    "title": "Music Program Overview",
    "description": "Explore our comprehensive music curriculum and offerings",
    "items": [
      {
        "id": "programs",
        "name": "Music Programs",
        "icon": "Music",
        "description": "Comprehensive offerings",
        "show": true
      },
      {
        "id": "ensembles",
        "name": "Ensembles",
        "icon": "Users",
        "description": "Performance groups",
        "show": true
      },
      {
        "id": "instruments",
        "name": "Instruments",
        "icon": "Guitar",
        "description": "What we teach",
        "show": true
      },
      {
        "id": "events",
        "name": "Events",
        "icon": "Calendar",
        "description": "Performances & competitions",
        "show": true
      }
    ]
  },
  "programs": {
    "show": true,
    "labels": {
      "programs": {
        "grades": "Grades",
        "description": "Description"
      },
      "ensembles": {
        "level": "Level",
        "director": "Director",
        "meeting": "Meeting"
      },
      "instruments": {
        "family": "Family",
        "instruments": "Instruments"
      },
      "events": {
        "date": "Date",
        "time": "Time",
        "location": "Location"
      }
    },
    "items": {
      "programs": [
        {
          "name": "Elementary Music",
          "icon": "Music",
          "grades": "K-5",
          "description": "Foundational music appreciation and basic instrument exposure",
          "learnMore": {
            "show": true,
            "text": "Learn more",
            "link": "#"
          },
          "show": true
        },
        {
          "name": "Middle School Band",
          "icon": "Drum",
          "grades": "6-8",
          "description": "Concert band, jazz band, and marching band fundamentals",
          "learnMore": {
            "show": true,
            "text": "Learn more",
            "link": "#"
          },
          "show": true
        },
        {
          "name": "High School Orchestra",
          "icon": "Music",
          "grades": "9-12",
          "description": "Symphonic orchestra and chamber music ensembles",
          "learnMore": {
            "show": true,
            "text": "Learn more",
            "link": "#"
          },
          "show": true
        },
        {
          "name": "Choral Program",
          "icon": "Mic",
          "grades": "4-12",
          "description": "Choirs for all experience levels from beginner to advanced",
          "learnMore": {
            "show": true,
            "text": "Learn more",
            "link": "#"
          },
          "show": true
        },
        {
          "name": "Music Theory",
          "icon": "Book",
          "grades": "9-12",
          "description": "AP Music Theory and composition classes",
          "learnMore": {
            "show": true,
            "text": "Learn more",
            "link": "#"
          },
          "show": true
        },
        {
          "name": "Digital Music Production",
          "icon": "Headphones",
          "grades": "9-12",
          "description": "Modern music technology and recording arts",
          "learnMore": {
            "show": true,
            "text": "Learn more",
            "link": "#"
          },
          "show": true
        }
      ],
      "ensembles": [
        {
          "name": "Concert Band",
          "icon": "Drum",
          "level": "Intermediate",
          "director": "Mr. Johnson",
          "meeting": "Mon/Wed 3:30-5:00 PM",
          "learnMore": {
            "show": true,
            "text": "Learn more",
            "link": "#"
          },
          "show": true
        },
        {
          "name": "Jazz Ensemble",
          "icon": "Music",
          "level": "Advanced",
          "director": "Ms. Davis",
          "meeting": "Tues/Thurs 3:30-5:30 PM",
          "learnMore": {
            "show": true,
            "text": "Learn more",
            "link": "#"
          },
          "show": true
        },
        {
          "name": "Symphonic Orchestra",
          "icon": "Music",
          "level": "Advanced",
          "director": "Mr. Chen",
          "meeting": "Mon/Tues/Thurs 3:30-5:30 PM",
          "learnMore": {
            "show": true,
            "text": "Learn more",
            "link": "#"
          },
          "show": true
        },
        {
          "name": "Concert Choir",
          "icon": "Mic",
          "level": "All Levels",
          "director": "Ms. Williams",
          "meeting": "Mon/Wed/Fri 3:30-5:00 PM",
          "learnMore": {
            "show": true,
            "text": "Learn more",
            "link": "#"
          },
          "show": true
        },
        {
          "name": "Chamber Singers",
          "icon": "Mic",
          "level": "Advanced",
          "director": "Ms. Williams",
          "meeting": "Tues/Thurs 4:00-6:00 PM",
          "learnMore": {
            "show": true,
            "text": "Learn more",
            "link": "#"
          },
          "show": true
        },
        {
          "name": "Percussion Ensemble",
          "icon": "Drum",
          "level": "Intermediate",
          "director": "Mr. Johnson",
          "meeting": "Fri 3:30-5:30 PM",
          "learnMore": {
            "show": true,
            "text": "Learn more",
            "link": "#"
          },
          "show": true
        }
      ],
      "instruments": [
        {
          "name": "Strings",
          "icon": "Music",
          "family": "Orchestral",
          "instruments": "Violin, Viola, Cello, Bass",
          "learnMore": {
            "show": true,
            "text": "Learn more",
            "link": "#"
          },
          "show": true
        },
        {
          "name": "Woodwinds",
          "icon": "Music",
          "family": "Band",
          "instruments": "Flute, Clarinet, Saxophone, Oboe, Bassoon",
          "learnMore": {
            "show": true,
            "text": "Learn more",
            "link": "#"
          },
          "show": true
        },
        {
          "name": "Brass",
          "icon": "Music",
          "family": "Band",
          "instruments": "Trumpet, Trombone, French Horn, Tuba, Euphonium",
          "learnMore": {
            "show": true,
            "text": "Learn more",
            "link": "#"
          },
          "show": true
        },
        {
          "name": "Percussion",
          "icon": "Drum",
          "family": "Band/Orchestra",
          "instruments": "Snare Drum, Timpani, Xylophone, Auxiliary",
          "learnMore": {
            "show": true,
            "text": "Learn more",
            "link": "#"
          },
          "show": true
        },
        {
          "name": "Piano",
          "icon": "Piano",
          "family": "All",
          "instruments": "Classical, Jazz, Contemporary",
          "learnMore": {
            "show": true,
            "text": "Learn more",
            "link": "#"
          },
          "show": true
        },
        {
          "name": "Guitar",
          "icon": "Guitar",
          "family": "Contemporary",
          "instruments": "Acoustic, Electric, Bass Guitar",
          "learnMore": {
            "show": true,
            "text": "Learn more",
            "link": "#"
          },
          "show": true
        }
      ],
      "events": [
        {
          "name": "Winter Concert",
          "icon": "Calendar",
          "date": "Dec 15, 2024",
          "time": "7:00 PM",
          "location": "School Auditorium",
          "learnMore": {
            "show": true,
            "text": "Learn more",
            "link": "#"
          },
          "show": true
        },
        {
          "name": "Solo & Ensemble Festival",
          "icon": "Trophy",
          "date": "Feb 22, 2024",
          "time": "9:00 AM",
          "location": "Music Wing",
          "learnMore": {
            "show": true,
            "text": "Learn more",
            "link": "#"
          },
          "show": true
        },
        {
          "name": "Spring Musical",
          "icon": "Calendar",
          "date": "Mar 20-23, 2024",
          "time": "7:00 PM",
          "location": "Main Theater",
          "learnMore": {
            "show": true,
            "text": "Learn more",
            "link": "#"
          },
          "show": true
        },
        {
          "name": "Jazz Night",
          "icon": "Music2",
          "date": "Apr 12, 2024",
          "time": "6:30 PM",
          "location": "Black Box Theater",
          "learnMore": {
            "show": true,
            "text": "Learn more",
            "link": "#"
          },
          "show": true
        },
        {
          "name": "State Music Competition",
          "icon": "Award",
          "date": "May 5-6, 2024",
          "time": "All Day",
          "location": "State University",
          "learnMore": {
            "show": true,
            "text": "Learn more",
            "link": "#"
          },
          "show": true
        },
        {
          "name": "Pops Concert",
          "icon": "Star",
          "date": "Jun 1, 2024",
          "time": "6:00 PM",
          "location": "Football Field",
          "learnMore": {
            "show": true,
            "text": "Learn more",
            "link": "#"
          },
          "show": true
        }
      ]
    }
  },
  "upcomingEvents": {
    "show": true,
    "title": "Upcoming Music Events",
    "description": "Mark your calendars for these exciting performances and activities",
    "labels": {
      "time": "Time",
      "location": "Location",
      "viewDetails": "View Details"
    },
    "items": [
      {
        "title": "Fall Choral Concert",
        "date": "2024-10-25",
        "time": "7:00 PM - 9:00 PM",
        "ensemble": "Concert Choir & Chamber Singers",
        "location": "School Auditorium",
        "description": "An evening of choral performances by our talented singers",
        "viewDetails": {
          "show": true,
          "text": "View Details",
          "link": "#"
        },
        "show": true
      },
      {
        "title": "Band Olympics",
        "date": "2024-11-08",
        "time": "4:00 PM - 7:00 PM",
        "ensemble": "All Band Students",
        "location": "Football Field",
        "description": "A fun-filled competition showcasing band skills",
        "viewDetails": {
          "show": true,
          "text": "View Details",
          "link": "#"
        },
        "show": true
      },
      {
        "title": "Middle School Music Night",
        "date": "2024-11-15",
        "time": "6:30 PM - 8:30 PM",
        "ensemble": "Middle School Bands & Choirs",
        "location": "Cafeteria",
        "description": "Performances by our middle school music ensembles",
        "viewDetails": {
          "show": true,
          "text": "View Details",
          "link": "#"
        },
        "show": true
      },
      {
        "title": "Orchestra Hall Field Trip",
        "date": "2024-12-05",
        "time": "9:00 AM - 4:00 PM",
        "ensemble": "Symphonic Orchestra",
        "location": "Downtown Concert Hall",
        "description": "A special trip to experience a professional orchestra",
        "viewDetails": {
          "show": true,
          "text": "View Details",
          "link": "#"
        },
        "show": true
      }
    ],
    "ctaButton": {
      "label": "View Full Events Calendar",
      "link": "#",
      "show": true
    }
  },
  "achievements": {
    "show": true,
    "title": "Recent Achievements",
    "description": "Celebrating the accomplishments of our talented student musicians",
    "items": [
      {
        "year": "2024",
        "items": [
          "Concert Band awarded 1st Place in State Competition",
          "12 students selected for All-State Honor Ensembles",
          "Jazz Ensemble received superior ratings at regional festival"
        ],
        "show": true
      },
      {
        "year": "2023",
        "items": [
          "Music Program recognized as Outstanding by State Association",
          "Chamber Singers invited to perform at national conference",
          "Student compositions published in national journal"
        ],
        "show": true
      },
      {
        "year": "2022",
        "items": [
          "Marching Band placed 2nd in State Championships",
          "Orchestra awarded Gold Rating at Heritage Festival",
          "Student won Young Composer Award"
        ],
        "show": true
      }
    ]
  },
  "faculty": {
    "show": true,
    "title": "Music Faculty",
    "labels": {
      "role": "Role",
      "qualification": "Qualification",
      "specialty": "Specialty",
      "experience": "Experience"
    },
    "items": [
      {
        "name": "Mr. Karan Mehra",
        "role": "Music Director",
        "qualification": "Sangeet Visharad, Trinity College Certified",
        "specialty": "Western Classical, Piano",
        "experience": "12 years",
        "show": true
      },
      {
        "name": "Ms. Sunita Devi",
        "role": "Indian Classical Music Instructor",
        "qualification": "M.A. in Indian Classical Music",
        "specialty": "Hindustani Vocal, Sitar",
        "experience": "15 years",
        "show": true
      },
      {
        "name": "Ms. Priya Sharma",
        "role": "Choral Director",
        "qualification": "M.M. in Choral Conducting",
        "specialty": "Choral Arranging, Vocal Pedagogy",
        "experience": "10 years",
        "show": true
      },
      {
        "name": "Mr. Ravi Verma",
        "role": "Instrumental Music Coordinator",
        "qualification": "B.M. in Music Education",
        "specialty": "Brass Instruments, Marching Band",
        "experience": "8 years",
        "show": true
      }
    ]
  },
  "resources": {
    "show": true,
    "title": "Music Resources",
    "description": "Download important documents, practice materials, and performance schedules",
    "items": [
      {
        "title": "Music Program Handbook",
        "description": "Policies, expectations, and calendar for all music students",
        "format": "PDF",
        "size": "1.8 MB",
        "icon": "FileText",
        "link": "#",
        "show": true
      },
      {
        "title": "Practice Schedule Templates",
        "description": "Weekly practice logs and goal-setting worksheets",
        "format": "PDF",
        "size": "0.7 MB",
        "icon": "FileText",
        "link": "#",
        "show": true
      },
      {
        "title": "Instrument Rental Guide",
        "description": "Information on acquiring and maintaining instruments",
        "format": "PDF",
        "size": "1.2 MB",
        "icon": "FileText",
        "link": "#",
        "show": true
      },
      {
        "title": "Upcoming Performances Calendar",
        "description": "Complete schedule of concerts and events for 2024-25",
        "format": "PDF",
        "size": "0.9 MB",
        "icon": "Calendar",
        "link": "#",
        "show": true
      }
    ]
  },
  "cta": {
    "show": true,
    "title": "Join Our Music Program",
    "description": "Whether you're a beginner or an experienced musician, there's a place for you in our music family",
    "buttons": [
      {
        "label": "Register for Music Classes",
        "link": "#",
        "show": true
      },
      {
        "label": "Contact Music Director",
        "link": "#",
        "show": true
      }
    ]
  },
  "contact": {
    "show": true,
    "title": "Music Department Contact",
    "items": [
      {
        "icon": "Phone",
        "label": "Phone",
        "value": "011-2336-3462 (Ext. 330)",
        "show": true
      },
      {
        "icon": "Mail",
        "label": "Email",
        "value": "music@stcolumbas.edu.in",
        "show": true
      },
      {
        "icon": "Clock",
        "label": "Office Hours",
        "value": "Mon-Fri: 9:00 AM - 5:00 PM",
        "show": true
      }
    ]
  },
  "general": {
    "learnMore": {
      "text": "Learn more",
      "link": "#",
      "show": true
    },
    "download": {
      "text": "Download",
      "link": "#",
      "show": true
    },
    "viewDetails": {
      "text": "View Details",
      "link": "#",
      "show": true
    }
  },
  "layout": {
    "showHero": true,
    "showBenefits": true,
    "showCategories": true,
    "showPrograms": true,
    "showUpcomingEvents": true,
    "showAchievements": true,
    "showFaculty": true,
    "showResources": true,
    "showCta": true,
    "showContact": true
  }
}